{
    "homepage": "https://github.com/sandboxie-plus/Sandboxie",
    "description": "Sandboxie is a sandbox-based isolation software for 32- and 64-bit Windows NT-based operating systems.",
    "version": "1.0.15",
    "license": "GPL-3.0 License",
    "architecture": {
        "64bit": {
            "url": "https://github.com/sandboxie-plus/Sandboxie/releases/download/1.0.15/Sandboxie-Plus-x64-v1.0.15.exe#/Sandboxie-install.exe",
            "hash": "97db922f94eb8ec992f33a16de9ada7dda2fd1e844ee8ef1ec7ec77de244d0dd",
            "installer": {
                "script": [
                    "Invoke-ExternalCommand \"$dir\\Sandboxie-install.exe\" -ArgumentList @('/install','/S',\"/D=$dir\") -RunAs | Out-Null",
                    "Remove-Item \"$dir\\Sandboxie-install.exe\" -Force -Recurse"
                ]
            },
            "uninstaller": {
                "script": [
                    "$uninstaller = (Get-Item Env:windir).Value+'\\installer\\SandboxieInstall64.exe'",
                    "Invoke-ExternalCommand \"$uninstaller\" -ArgumentList @('/remove','/S') -RunAs | Out-Null"
                ]
            }
        },
        "32bit": {
            "url": "https://github.com/sandboxie-plus/Sandboxie/releases/download/1.0.15/Sandboxie-Plus-x86-v1.0.15.exe#/Sandboxie-install.exe",
            "hash": "2c4427d0824d5f0758dd4cb94724e07549910067910179a2dae8256cc32791db",
            "installer": {
                "script": [
                    "Invoke-ExternalCommand \"$dir\\Sandboxie-install.exe\" -ArgumentList @('/install','/S',\"/D=$dir\") -RunAs | Out-Null",
                    "Remove-Item \"$dir\\Sandboxie-install.exe\" -Force -Recurse"
                ]
            },
            "uninstaller": {
                "script": [
                    "$uninstaller = (Get-Item Env:windir).Value+'\\installer\\SandboxieInstall.exe'",
                    "Invoke-ExternalCommand \"$uninstaller\" -ArgumentList @('/remove','/S') -RunAs | Out-Null"
                ]
            }
        }
    },
    "shortcuts": [
        [
            "Sandboxie-Plus\\SandMan.exe",
            "SandboxiePlus"
        ]
    ],
    "checkver": {
        "url": "https://github.com/sandboxie-plus/Sandboxie",
        "regex": "<span class=\"css-truncate css-truncate-target text-bold mr-2\" style=\"max-width: none;\">Release v([\\d.]+) /"
    },
    "autoupdate": {
        "architecture": {
            "64bit": {
                "url": "https://github.com/sandboxie-plus/Sandboxie/releases/download/$version/Sandboxie-Plus-x64-v$version.exe#/Sandboxie-install.exe"
            },
            "32bit": {
                "url": "https://github.com/sandboxie-plus/Sandboxie/releases/download/$version/Sandboxie-Plus-x86-v$version.exe#/Sandboxie-install.exe"
            }
        }
    }
}
